vimvaldi/__init__.py
vimvaldi/commands.py
vimvaldi/components.py
vimvaldi/graphics.py
vimvaldi/music.py
vimvaldi/utilities.py
vimvaldi-0.1.2.data/data/DOCUMENTATION.md
vimvaldi-0.1.2.data/data/LICENSE.txt
vimvaldi-0.1.2.data/data/README.md
vimvaldi-0.1.2.dist-info/LICENSE.txt
vimvaldi-0.1.2.dist-info/METADATA
vimvaldi-0.1.2.dist-info/WHEEL
vimvaldi-0.1.2.dist-info/entry_points.txt
vimvaldi-0.1.2.dist-info/top_level.txt
vimvaldi-0.1.2.dist-info/RECORD
