Metadata-Version: 2.1
Name: vimvaldi
Version: 0.1.2
Summary: A terminal note sheet editor.
Home-page: https://github.com/xiaoxiae/Vimvaldi
Author: Tomáš Sláma
Author-email: tomas@slama.dev
License: UNKNOWN
Keywords: notes notesheet editor curses
Platform: UNKNOWN
Classifier: Programming Language :: Python :: 3
Classifier: License :: OSI Approved :: MIT License
Classifier: Operating System :: OS Independent
Requires-Python: >=3.7
Requires-Dist: abjad
